SimplePyTorchUtils/__init__.py
SimplePyTorchUtils/main.py
SimplePyTorchUtils-0.0.2.dist-info/LICENSE
SimplePyTorchUtils-0.0.2.dist-info/METADATA
SimplePyTorchUtils-0.0.2.dist-info/WHEEL
SimplePyTorchUtils-0.0.2.dist-info/top_level.txt
SimplePyTorchUtils-0.0.2.dist-info/RECORD
