Metadata-Version: 2.1
Name: SimplePyTorchUtils
Version: 0.0.2
Summary: A collection of simple tools for working with PyTorch
Home-page: https://github.com/gr1336/SimplePyTorchUtils/
Author: gr1336
License: Apache Software License
Classifier: Topic :: Software Development
Classifier: Topic :: Software Development :: Libraries
Classifier: Topic :: Software Development :: Testing
Classifier: Topic :: Software Development :: Pre-processors
Classifier: Topic :: Utilities
Classifier: License :: OSI Approved :: Apache Software License
License-File: LICENSE
Requires-Dist: torch >=2.0.0
Requires-Dist: numpy
